nbproject/__init__.py
nbproject/__main__.py
nbproject/_cli.py
nbproject/_header.py
nbproject/_is_run_from_ipython.py
nbproject/_logger.py
nbproject/_meta.py
nbproject/_publish.py
nbproject/_schemas.py
nbproject/dev/__init__.py
nbproject/dev/_check_last_cell.py
nbproject/dev/_classic_nb_commands.py
nbproject/dev/_consecutiveness.py
nbproject/dev/_frontend_commands.py
nbproject/dev/_initialize.py
nbproject/dev/_jupyter_communicate.py
nbproject/dev/_jupyter_lab_commands.py
nbproject/dev/_lamin_communicate.py
nbproject/dev/_meta_live.py
nbproject/dev/_meta_store.py
nbproject/dev/_metadata_display.py
nbproject/dev/_notebook.py
nbproject/dev/_pypackage.py
nbproject/dev/_set_version.py
nbproject-0.11.1.dist-info/entry_points.txt
nbproject-0.11.1.dist-info/LICENSE
nbproject-0.11.1.dist-info/WHEEL
nbproject-0.11.1.dist-info/METADATA
nbproject-0.11.1.dist-info/RECORD
