Metadata-Version: 2.3
Name: nbproject
Version: 0.11.1
Summary: nbproject: Manage Jupyter notebooks.
Author-email: Lamin Labs <laminlabs@gmail.com>
Classifier: License :: OSI Approved :: Apache Software License
Classifier: Programming Language :: Python :: 3.8
Classifier: Programming Language :: Python :: 3.9
Classifier: Programming Language :: Python :: 3.10
Classifier: Programming Language :: Python :: 3.11
Requires-Dist: pydantic>=2.0.0
Requires-Dist: pyyaml
Requires-Dist: packaging
Requires-Dist: orjson
Requires-Dist: psutil
Requires-Dist: importlib-metadata
Requires-Dist: stdlib_list; python_version < '3.10'
Requires-Dist: lamin_utils>=0.13.2
Requires-Dist: pre-commit ; extra == "dev"
Requires-Dist: black ; extra == "dev"
Requires-Dist: pytest>=6.0 ; extra == "dev"
Requires-Dist: pytest-cov ; extra == "dev"
Requires-Dist: pandas ; extra == "dev"
Requires-Dist: nbformat ; extra == "dev"
Requires-Dist: nbproject_test >= 0.4.5 ; extra == "dev"
Requires-Dist: laminci ; extra == "dev"
Requires-Dist: ipylab ; extra == "dev"
Requires-Dist: nbconvert ; extra == "dev"
Project-URL: Home, https://github.com/laminlabs/nbproject
Provides-Extra: dev
